CHANGELOG.txt
LICENCE.txt
MANIFEST.in
README.md
setup.py
mail-man/Lib/site-packages/_distutils_hack/__init__.py
mail-man/Lib/site-packages/_distutils_hack/override.py
mail-man/Lib/site-packages/backports/__init__.py
mail-man/Lib/site-packages/backports.tarfile-1.2.0.dist-info/top_level.txt
mail-man/Lib/site-packages/backports/tarfile/__init__.py
mail-man/Lib/site-packages/backports/tarfile/__main__.py
mail-man/Lib/site-packages/backports/tarfile/compat/__init__.py
mail-man/Lib/site-packages/backports/tarfile/compat/py38.py
mail-man/Lib/site-packages/certifi/__init__.py
mail-man/Lib/site-packages/certifi/__main__.py
mail-man/Lib/site-packages/certifi/core.py
mail-man/Lib/site-packages/certifi-2024.6.2.dist-info/top_level.txt
mail-man/Lib/site-packages/charset_normalizer/__init__.py
mail-man/Lib/site-packages/charset_normalizer/__main__.py
mail-man/Lib/site-packages/charset_normalizer/api.py
mail-man/Lib/site-packages/charset_normalizer/cd.py
mail-man/Lib/site-packages/charset_normalizer/constant.py
mail-man/Lib/site-packages/charset_normalizer/legacy.py
mail-man/Lib/site-packages/charset_normalizer/md.py
mail-man/Lib/site-packages/charset_normalizer/models.py
mail-man/Lib/site-packages/charset_normalizer/utils.py
mail-man/Lib/site-packages/charset_normalizer/version.py
mail-man/Lib/site-packages/charset_normalizer-3.3.2.dist-info/entry_points.txt
mail-man/Lib/site-packages/charset_normalizer-3.3.2.dist-info/top_level.txt
mail-man/Lib/site-packages/charset_normalizer/cli/__init__.py
mail-man/Lib/site-packages/charset_normalizer/cli/__main__.py
mail-man/Lib/site-packages/docutils/__init__.py
mail-man/Lib/site-packages/docutils/__main__.py
mail-man/Lib/site-packages/docutils/core.py
mail-man/Lib/site-packages/docutils/examples.py
mail-man/Lib/site-packages/docutils/frontend.py
mail-man/Lib/site-packages/docutils/io.py
mail-man/Lib/site-packages/docutils/nodes.py
mail-man/Lib/site-packages/docutils/statemachine.py
mail-man/Lib/site-packages/docutils-0.21.2.dist-info/COPYING.txt
mail-man/Lib/site-packages/docutils-0.21.2.dist-info/entry_points.txt
mail-man/Lib/site-packages/docutils/languages/__init__.py
mail-man/Lib/site-packages/docutils/languages/af.py
mail-man/Lib/site-packages/docutils/languages/ar.py
mail-man/Lib/site-packages/docutils/languages/ca.py
mail-man/Lib/site-packages/docutils/languages/cs.py
mail-man/Lib/site-packages/docutils/languages/da.py
mail-man/Lib/site-packages/importlib_metadata-7.1.0.dist-info/top_level.txt
mail-man/Lib/site-packages/jaraco.classes-3.4.0.dist-info/top_level.txt
mail-man/Lib/site-packages/jaraco.context-5.3.0.dist-info/top_level.txt
mail-man/Lib/site-packages/jaraco.functools-4.0.1.dist-info/top_level.txt
mail-man/Lib/site-packages/keyring-25.2.1.dist-info/entry_points.txt
mail-man/Lib/site-packages/keyring-25.2.1.dist-info/top_level.txt
mail-man/Lib/site-packages/markdown_it_py-3.0.0.dist-info/entry_points.txt
mail-man/Lib/site-packages/pip-24.0.dist-info/AUTHORS.txt
mail-man/Lib/site-packages/pip-24.0.dist-info/LICENSE.txt
mail-man/Lib/site-packages/pip-24.0.dist-info/entry_points.txt
mail-man/Lib/site-packages/pip-24.0.dist-info/top_level.txt
mail-man/Lib/site-packages/pkginfo-1.11.0.dist-info/LICENSE.txt
mail-man/Lib/site-packages/pkginfo-1.11.0.dist-info/entry_points.txt
mail-man/Lib/site-packages/pkginfo-1.11.0.dist-info/top_level.txt
mail-man/Lib/site-packages/pygments-2.18.0.dist-info/entry_points.txt
mail-man/Lib/site-packages/pywin32_ctypes-0.2.2.dist-info/LICENSE.txt
mail-man/Lib/site-packages/pywin32_ctypes-0.2.2.dist-info/top_level.txt
mail-man/Lib/site-packages/readme_renderer-43.0.dist-info/top_level.txt
mail-man/Lib/site-packages/requests-2.32.3.dist-info/top_level.txt
mail-man/Lib/site-packages/requests_toolbelt-1.0.0.dist-info/top_level.txt
mail-man/Lib/site-packages/rfc3986-2.0.0.dist-info/top_level.txt
mail-man/Lib/site-packages/setuptools-70.0.0.dist-info/entry_points.txt
mail-man/Lib/site-packages/setuptools-70.0.0.dist-info/top_level.txt
mail-man/Lib/site-packages/twine-5.1.0.dist-info/entry_points.txt
mail-man/Lib/site-packages/twine-5.1.0.dist-info/top_level.txt
mail-man/Lib/site-packages/urllib3-2.2.1.dist-info/licenses/LICENSE.txt
mail-man/Lib/site-packages/wheel-0.43.0.dist-info/LICENSE.txt
mail-man/Lib/site-packages/wheel-0.43.0.dist-info/entry_points.txt
mail-man/Lib/site-packages/zipp-3.19.2.dist-info/top_level.txt
test_library.egg-info/SOURCES.txt
test_library.egg-info/dependency_links.txt
test_library.egg-info/top_level.txt
test_library_001_78090930934.egg-info/PKG-INFO
test_library_001_78090930934.egg-info/SOURCES.txt
test_library_001_78090930934.egg-info/dependency_links.txt
test_library_001_78090930934.egg-info/top_level.txt
