Metadata-Version: 2.1
Name: test-library-001-78090930934
Version: 0.1
Summary: Library example
Home-page: 
Author: noel-mr-cabysis
Author-email: noel.munoz@cabysis.com
License-File: LICENCE.txt
